{
  "nodes": [
    {"id": "A", "exit": false, "x": 100, "y": 100, "name": "Reception"},
    {"id": "B", "exit": false, "x": 200, "y": 100, "name": "Main Hallway"},
    {"id": "C", "exit": false, "x": 300, "y": 100, "name": "Conference Room"},
    {"id": "D", "exit": false, "x": 200, "y": 200, "name": "Office Area 1"},
    {"id": "E", "exit": false, "x": 300, "y": 200, "name": "Office Area 2"},
    {"id": "F", "exit": false, "x": 400, "y": 200, "name": "Storage Room 1"},
    {"id": "G", "exit": false, "x": 400, "y": 100, "name": "Break Room"},
    {"id": "H", "exit": false, "x": 500, "y": 100, "name": "Restrooms"},
    {"id": "I", "exit": false, "x": 500, "y": 200, "name": "IT Department"},
    {"id": "J", "exit": false, "x": 600, "y": 100, "name": "Meeting Room 1"},
    {"id": "K", "exit": false, "x": 600, "y": 200, "name": "Meeting Room 2"},
    {"id": "L", "exit": false, "x": 100, "y": 200, "name": "Security Office"},
    {"id": "M", "exit": false, "x": 100, "y": 300, "name": "Locker Room"},
    {"id": "N", "exit": false, "x": 200, "y": 300, "name": "Cafeteria"},
    {"id": "O", "exit": false, "x": 300, "y": 300, "name": "Kitchen"},
    {"id": "P", "exit": false, "x": 400, "y": 300, "name": "Storage Room 2"},
    {"id": "Q", "exit": false, "x": 500, "y": 300, "name": "Server Room"},
    {"id": "R", "exit": false, "x": 600, "y": 300, "name": "Supply Closet"},
    {"id": "S", "exit": true, "x": 700, "y": 100, "name": "Main Exit"},
    {"id": "T", "exit": true, "x": 700, "y": 300, "name": "Emergency Exit 1"},
    {"id": "U", "exit": true, "x": 300, "y": 400, "name": "Emergency Exit 2"},
    {"id": "V", "exit": false, "x": 400, "y": 400, "name": "Maintenance Room"},
    {"id": "W", "exit": false, "x": 500, "y": 400, "name": "Archive Room"},
    {"id": "X", "exit": false, "x": 600, "y": 400, "name": "Records Room"},
    {"id": "Y", "exit": false, "x": 200, "y": 400, "name": "Electrical Room"},
    {"id": "Z", "exit": false, "x": 100, "y": 400, "name": "Janitor Closet"}
  ],
  "edges": [
    {"from": "A", "to": "B"},
    {"from": "B", "to": "C"},
    {"from": "B", "to": "D"},
    {"from": "C", "to": "G"},
    {"from": "D", "to": "E"},
    {"from": "E", "to": "F"},
    {"from": "E", "to": "I"},
    {"from": "G", "to": "H"},
    {"from": "H", "to": "I"},
    {"from": "H", "to": "J"},
    {"from": "I", "to": "K"},
    {"from": "J", "to": "S"},
    {"from": "K", "to": "R"},
    {"from": "A", "to": "L"},
    {"from": "L", "to": "M"},
    {"from": "D", "to": "N"},
    {"from": "N", "to": "O"},
    {"from": "E", "to": "O"},
    {"from": "F", "to": "P"},
    {"from": "I", "to": "Q"},
    {"from": "K", "to": "R"},
    {"from": "M", "to": "Z"},
    {"from": "N", "to": "Y"},
    {"from": "O", "to": "U"},
    {"from": "P", "to": "V"},
    {"from": "Q", "to": "W"},
    {"from": "R", "to": "X"},
    {"from": "R", "to": "T"},
    {"from": "V", "to": "W"},
    {"from": "Y", "to": "U"},
    {"from": "Z", "to": "Y"}
  ]
}